Full_Subtractor/full_subtractor.v
module full_subtractor (
    input wire a, 
    input wire b, 
    input wire bin, // Borrow in
    output wire d, // Difference
    output wire bout // Borrow out
);
    
    assign d = a ^ b ^ bin; // Difference calculation
    assign bout = (~a & (b | bin)) | (b & bin); // Borrow out calculation
    
endmodule

Full_Subtractor/full_subtractor_tb.v
module full_subtractor_tb (
    );
    
    reg a, b, bin; // Inputs
    wire d, bout; // Outputs
    
    // Instantiate the full subtractor module
    full_subtractor fs (
        .a(a),
        .b(b),
        .bin(bin),
        .d(d),
        .bout(bout)
    );
    
    initial begin
        // Test all combinations of inputs
        $monitor("a=%b, b=%b, bin=%b | d=%b, bout=%b", a, b, bin, d, bout);
        
        a = 0; b = 0; bin = 0; #10;
        a = 0; b = 0; bin = 1; #10;
        a = 0; b = 1; bin = 0; #10;
        a = 0; b = 1; bin = 1; #10;
        a = 1; b = 0; bin = 0; #10;
        a = 1; b = 0; bin = 1; #10;
        a = 1; b = 1; bin = 0; #10;
        a = 1; b = 1; bin = 1; #10;
        
        $finish;
    end
    
    initial begin
        $dumpfile("full_subtractor_tb.vcd");
        $dumpvars(0, full_subtractor_tb);
    end
endmodule

Full_Subtractor/full_subtractor_tb.vcd
$date
	Tue Apr 22 15:42:09 2025
$end
$version
	Icarus Verilog
$end
$timescale
	1s
$end
$scope module full_subtractor_tb $end
$var wire 1 ! d $end
$var wire 1 " bout $end
$var reg 1 # a $end
$var reg 1 $ b $end
$var reg 1 % bin $end
$scope module fs $end
$var wire 1 # a $end
$var wire 1 $ b $end
$var wire 1 % bin $end
$var wire 1 " bout $end
$var wire 1 ! d $end
$upscope $end
$upscope $end
$enddefinitions $end
$comment Show the parameter values. $end
$dumpall
$end
#0
$dumpvars
0%
0$
0#
0"
0!
$end
#10
1"
1!
1%
#20
0%
1$
#30
0!
1%
#40
0"
1!
0%
0$
1#
#50
0!
1%
#60
0%
1$
#70
1"
1!
1%
