Full_Adder_using_Half_Adder/full_adder_using_half_adder.v
module full_adder_using_half_adder (
    input a, b, cin,
    output sum, cout
);
    wire s1, c1, c2;

    // First half adder
    assign s1 = a ^ b; // Sum of first half adder
    assign c1 = a & b; // Carry of first half adder

    // Second half adder
    assign sum = s1 ^ cin; // Final sum
    assign c2 = s1 & cin; // Carry of second half adder

    // Final carry out
    assign cout = c1 | c2; 
    
endmodule

Full_Adder_using_Half_Adder/full_adder_using_half_adder_tb.v
module full_adder_using_half_adder_tb ();
    // Inputs
    reg a;
    reg b;
    reg cin;

    // Outputs
    wire sum;
    wire cout;

    // Instantiate the full adder using half adder module
    full_adder_using_half_adder uut (
        .a(a),
        .b(b),
        .cin(cin),
        .sum(sum),
        .cout(cout)
    );
    initial begin
        $dumpfile("full_adder_using_half_adder.vcd"); // Specify the VCD file name
        $dumpvars(0, uut); // Dump all variables in this module
    end
    // Test cases
    initial begin
        // Test case 1: 0 + 0 + 0 = 0, cout = 0
        a = 0; b = 0; cin = 0;
        #10; // Wait for 10 time units

        // Test case 2: 0 + 0 + 1 = 1, cout = 0
        a = 0; b = 0; cin = 1;
        #10;

        // Test case 3: 0 + 1 + 0 = 1, cout = 0
        a = 0; b = 1; cin = 0;
        #10;

        // Test case 4: 0 + 1 + 1 = 2, cout = 1
        a = 0; b = 1; cin = 1;
        #10;

        // Test case 5: 1 + 0 + 0 = 1, cout = 0
        a = 1; b = 0; cin = 0;
        #10;

        // Test case 6: 1 + 0 + 1 = 2, cout = 1
        a = 1; b = 0; cin = 1;
        #10;

        // Test case 7: 1 + 1 + 0 = 2, cout = 1
        a = 1; b = 1; cin = 0;
        #10;

        // Test case 8: All inputs are high (1 + 1 + 1)
        a = 1; b = 1; cin = 1;
        #10;

        $finish; // End the simulation
    end

    initial begin
        $monitor("Time=%d | a=%b | b=%b | cin=%b | sum=%b | cout=%b", $time, a, b, cin, sum, cout);
    end

    
endmodule

Full_Adder_using_Half_Adder/full_adder_using_half_adder.vcd
$date
	Sat Apr 19 11:50:58 2025
$end
$version
	Icarus Verilog
$end
$timescale
	1s
$end
$scope module full_adder_using_half_adder_tb $end
$scope module uut $end
$var wire 1 ! a $end
$var wire 1 " b $end
$var wire 1 # c1 $end
$var wire 1 $ c2 $end
$var wire 1 % cin $end
$var wire 1 & cout $end
$var wire 1 ' s1 $end
$var wire 1 ( sum $end
$upscope $end
$upscope $end
$enddefinitions $end
$comment Show the parameter values. $end
$dumpall
$end
#0
$dumpvars
0(
0'
0&
0%
0$
0#
0"
0!
$end
#10
1(
1%
#20
1'
0%
1"
#30
1&
0(
1$
1%
#40
0&
1(
0$
0%
0"
1!
#50
1&
0(
1$
1%
#60
0$
0'
1#
0%
1"
#70
1(
1%
