4_bit_even_parity_generator/four_bit_even_parity.v
module four_bit_even_parity (
    input [3:0] data_in, // 4-bit input data
    output parity_out // Even parity output
);
    // Calculate even parity by XORing all bits of the input data
    assign parity_out = data_in[0] ^ data_in[1] ^ data_in[2] ^ data_in[3];
    
endmodule

4_bit_even_parity_generator/four_bit_even_parity_tb.v
`timescale 1ns / 1ps

module four_bit_even_parity_tb;

    // Testbench signals
    reg [3:0] data_in;
    wire parity_out;

    // Instantiate the Unit Under Test (UUT)
    four_bit_even_parity uut (
        .data_in(data_in),
        .parity_out(parity_out)
    );

    initial begin
        $dumpfile("parity.vcd");
        $dumpvars(0, four_bit_even_parity_tb);
        $display("Time\tData In\tParity");
        $monitor("%0dns\t%b\t%b", $time, data_in, parity_out);

        // Test all 4-bit input combinations (0 to 15)
        data_in = 4'b0000; #10;
        data_in = 4'b0001; #10;
        data_in = 4'b0010; #10;
        data_in = 4'b0011; #10;
        data_in = 4'b0100; #10;
        data_in = 4'b0101; #10;
        data_in = 4'b0110; #10;
        data_in = 4'b0111; #10;
        data_in = 4'b1000; #10;
        data_in = 4'b1001; #10;
        data_in = 4'b1010; #10;
        data_in = 4'b1011; #10;
        data_in = 4'b1100; #10;
        data_in = 4'b1101; #10;
        data_in = 4'b1110; #10;
        data_in = 4'b1111; #10;

        $finish;
    end

endmodule

4_bit_even_parity_generator/parity.vcd
$date
	Wed Apr 16 07:12:17 2025
$end
$version
	Icarus Verilog
$end
$timescale
	1ps
$end
$scope module four_bit_even_parity_tb $end
$var wire 1 ! parity_out $end
$var reg 4 " data_in [3:0] $end
$scope module uut $end
$var wire 4 # data_in [3:0] $end
$var wire 1 ! parity_out $end
$upscope $end
$upscope $end
$enddefinitions $end
$comment Show the parameter values. $end
$dumpall
$end
#0
$dumpvars
b0 #
b0 "
0!
$end
#10000
1!
b1 "
b1 #
#20000
b10 "
b10 #
#30000
0!
b11 "
b11 #
#40000
1!
b100 "
b100 #
#50000
0!
b101 "
b101 #
#60000
b110 "
b110 #
#70000
1!
b111 "
b111 #
#80000
1!
b1000 "
b1000 #
#90000
0!
b1001 "
b1001 #
#100000
b1010 "
b1010 #
#110000
1!
b1011 "
b1011 #
#120000
0!
b1100 "
b1100 #
#130000
1!
b1101 "
b1101 #
#140000
b1110 "
b1110 #
#150000
0!
b1111 "
b1111 #
