Full_Adder/full_adder.v
`timescale 1ns / 1ps
module full_adder (
    input wire a, // First input bit
    input wire b, // Second input bit
    input wire cin, // Carry-in bit
    output wire sum, // Sum output bit
    output wire cout // Carry-out bit
);

    // Sum is the XOR of a, b and cin
    assign sum = a ^ b ^ cin;

    // Carry-out is true if at least two of the inputs are true
    assign cout = (a & b) | (cin & (a ^ b));
    
endmodule

Full_Adder/full_adder_tb.v
`timescale 1ns / 1ps

module full_adder_tb;

    // Testbench inputs
    reg a;
    reg b;
    reg cin;

    // Testbench outputs
    wire sum;
    wire cout;

    // Instantiate the full adder module
    full_adder uut (
        .a(a),
        .b(b),
        .cin(cin),
        .sum(sum),
        .cout(cout)
    );

    // VCD dump
initial begin
    $dumpfile("full_adder.vcd");
    $dumpvars(0, uut); // Dump the instance, not the module name
end
    // Apply test vectors
    initial begin
        a = 0; b = 0; cin = 0;
        #10 a = 0; b = 0; cin = 1;
        #10 a = 0; b = 1; cin = 0;
        #10 a = 0; b = 1; cin = 1;
        #10 a = 1; b = 0; cin = 0;
        #10 a = 1; b = 0; cin = 1;
        #10 a = 1; b = 1; cin = 0;
        #10 a = 1; b = 1; cin = 1;
        #10 $finish;
    end

    // Monitor changes
    initial begin
        $monitor("Time=%0t: a=%b b=%b cin=%b | sum=%b cout=%b", $time, a, b, cin, sum, cout);
    end

endmodule

Full_Adder/full_adder.vcd
$date
	Sat Apr 19 10:30:31 2025
$end
$version
	Icarus Verilog
$end
$timescale
	1ps
$end
$scope module full_adder_tb $end
$scope module uut $end
$var wire 1 ! a $end
$var wire 1 " b $end
$var wire 1 # cin $end
$var wire 1 $ cout $end
$var wire 1 % sum $end
$upscope $end
$upscope $end
$enddefinitions $end
$comment Show the parameter values. $end
$dumpall
$end
#0
$dumpvars
0%
0$
0#
0"
0!
$end
#10000
1%
1#
#20000
0#
1"
#30000
1$
0%
1#
#40000
0$
1%
0#
0"
1!
#50000
1$
0%
1#
#60000
0#
1"
#70000
1%
1#
