Binary to GreyCode/binary_to_grey_code.v
module binary_to_grey_code (
    
    input [3:0] binary_in, // 4-bit binary input
    output reg [3:0] grey_out // 4-bit grey code output
);

    always @(*) begin
        grey_out[3] = binary_in[3]; // MSB remains the same
        grey_out[2] = binary_in[3] ^ binary_in[2]; // XOR of MSB and next bit
        grey_out[1] = binary_in[2] ^ binary_in[1]; // XOR of next two bits
        grey_out[0] = binary_in[1] ^ binary_in[0]; // XOR of LSB and next bit
    end
    
endmodule

Binary to GreyCode/binary_to_grey_code_tb.v
`timescale 1ns / 1ps

module binary_to_grey_code_tb;

    // Testbench signals
    reg [3:0] binary_in;
    wire [3:0] grey_out;

    // Instantiate the Unit Under Test (UUT)
    binary_to_grey_code uut (
        .binary_in(binary_in),
        .grey_out(grey_out)
    );

    // Test sequence
    initial begin
            $dumpfile("waveform.vcd");
        $dumpvars(0, binary_to_grey_code_tb);

        $display("Time\tBinary\tGray");
        $monitor("%0dns\t%b\t%b", $time, binary_in, grey_out);

        // Test all 4-bit binary values
        binary_in = 4'b0000; #10;
        binary_in = 4'b0001; #10;
        binary_in = 4'b0010; #10;
        binary_in = 4'b0011; #10;
        binary_in = 4'b0100; #10;
        binary_in = 4'b0101; #10;
        binary_in = 4'b0110; #10;
        binary_in = 4'b0111; #10;
        binary_in = 4'b1000; #10;
        binary_in = 4'b1001; #10;
        binary_in = 4'b1010; #10;
        binary_in = 4'b1011; #10;
        binary_in = 4'b1100; #10;
        binary_in = 4'b1101; #10;
        binary_in = 4'b1110; #10;
        binary_in = 4'b1111; #10;

        $finish;
    end

endmodule

Binary to GreyCode/waveform.vcd
$date
	Wed Apr 16 06:53:47 2025
$end
$version
	Icarus Verilog
$end
$timescale
	1ps
$end
$scope module binary_to_grey_code_tb $end
$var wire 4 ! grey_out [3:0] $end
$var reg 4 " binary_in [3:0] $end
$scope module uut $end
$var wire 4 # binary_in [3:0] $end
$var reg 4 $ grey_out [3:0] $end
$upscope $end
$upscope $end
$enddefinitions $end
$comment Show the parameter values. $end
$dumpall
$end
#0
$dumpvars
b0 $
b0 #
b0 "
b0 !
$end
#10000
b1 !
b1 $
b1 "
b1 #
#20000
b11 !
b11 $
b10 "
b10 #
#30000
b10 !
b10 $
b11 "
b11 #
#40000
b110 !
b110 $
b100 "
b100 #
#50000
b111 !
b111 $
b101 "
b101 #
#60000
b101 !
b101 $
b110 "
b110 #
#70000
b100 !
b100 $
b111 "
b111 #
#80000
b1100 !
b1100 $
b1000 "
b1000 #
#90000
b1101 !
b1101 $
b1001 "
b1001 #
#100000
b1111 !
b1111 $
b1010 "
b1010 #
#110000
b1110 !
b1110 $
b1011 "
b1011 #
#120000
b1010 !
b1010 $
b1100 "
b1100 #
#130000
b1011 !
b1011 $
b1101 "
b1101 #
#140000
b1001 !
b1001 $
b1110 "
b1110 #
#150000
b1000 !
b1000 $
b1111 "
b1111 #
